instruction_memory_pc/instruction_memory_pc.sv
 module instruction_memory_pc(input logic [7:0] immediate,
                              input logic PCSrc,CLK,reset,
                              output logic [23:0] instr);


logic [23:0] data_ROM [0:255];
initial $readmemh("program.txt", data_ROM);
assign instr = data_ROM[PC];
logic [7:0] PC;



always_ff @ (posedge CLK) 
    begin
        if (reset) PC <= 8'd0;
        else PC <= (PCSrc)? immediate: PC + 8'd1;
    end
// try with out file 



endmodule

instruction_memory_pc/instruction_memory_pc_tb.sv
`timescale 1ns/1ps // Define time units and resolution
`include "instruction_memory_pc.sv" // Include all modules being used in this module

module instruction_memory_pc_tb;
logic [7:0] immediate;
logic PCSrc,CLK,reset;
logic [23:0] instr;
instruction_memory_pc dut(immediate,PCSrc,CLK,reset,instr); // Instantiate the module under test

initial begin // Single pass behaviour which starts at time 0 ns
$dumpfile("instruction_memory_pc_tb.vcd"); // Dump variable changes in the vcd file
$dumpvars(0, instruction_memory_pc_tb); // Specifies which variables to dump in the vcd file
$display("this works");

reset =1; immediate = 0; PCSrc = 0; CLK = 0; #20; 
CLK=1; #20;


reset = 0; #20;

for(int i = 0; i<8;i++)
    begin
       $display("instr = %h", instr);  
        CLK = 0; #20;
        CLK = 1; #20;

    end

end

/*
initial begin
$monitor("t = %3d,CLK = %b, reset = %b, PCSrc = %b, immediate = %b, instr = %h \n", $time, CLK, reset, PCSrc, immediate, instr);
end // Print variable
// values on screen
*/
endmodule

instruction_memory_pc/instruction_memory_pc_tb.vcd
$date
	Tue Feb 13 17:52:07 2024
$end
$version
	Icarus Verilog
$end
$timescale
	1ps
$end
$scope module instruction_memory_pc_tb $end
$var wire 24 ! instr [23:0] $end
$var reg 1 " CLK $end
$var reg 1 # PCSrc $end
$var reg 8 $ immediate [7:0] $end
$var reg 1 % reset $end
$scope module dut $end
$var wire 1 " CLK $end
$var wire 1 # PCSrc $end
$var wire 8 & immediate [7:0] $end
$var wire 24 ' instr [23:0] $end
$var wire 1 % reset $end
$var reg 8 ( PC [7:0] $end
$upscope $end
$scope begin $ivl_for_loop0 $end
$var integer 32 ) i [31:0] $end
$upscope $end
$upscope $end
$enddefinitions $end
$comment Show the parameter values. $end
$dumpall
$end
#0
$dumpvars
b0 )
bx (
bx '
b0 &
1%
b0 $
0#
0"
bx !
$end
#20000
b11000010000000000000001 !
b11000010000000000000001 '
b0 (
1"
#40000
0%
#60000
0"
#80000
b11000100000000000100000 !
b11000100000000000100000 '
b1 (
1"
#100000
0"
b1 )
#120000
b11011110000000000000000 !
b11011110000000000000000 '
b10 (
1"
#140000
0"
b10 )
#160000
b11100000001001000000111 !
b11100000001001000000111 '
b11 (
1"
#180000
0"
b11 )
#200000
b1000010001000100000000 !
b1000010001000100000000 '
b100 (
1"
#220000
0"
b100 )
#240000
b11011111111000000000001 !
b11011111111000000000001 '
b101 (
1"
#260000
0"
b101 )
#280000
b11100000000000000000011 !
b11100000000000000000011 '
b110 (
1"
#300000
0"
b110 )
#320000
b11100000000000000000111 !
b11100000000000000000111 '
b111 (
1"
#340000
0"
b111 )
#360000
bx !
bx '
b1000 (
1"
#380000
b1000 )
