register/reg_file.sv
module reg_file (input logic [3:0] RA1, RA2, WA, 
                 input logic [7:0] ALUResult,
                 input logic write_enable,
                 input logic CLK,
                 output logic [7:0] RD1, RD2, cpu_out);

// define registers -> width of data -> number of addresses
reg [7:0] register [0:15];

//assign register[0] = 0; // set x0 to 0 

// continous assignment 
assign RD1 = register[RA1];
assign RD2 = register[RA2];
assign cpu_out = register[15];
//assign register[0] = 0;

always_ff @ (posedge CLK)
begin

// write to register at address given by WA
if(write_enable && (WA>0)) register[WA] <= ALUResult;
register[0] <= 0;

end

endmodule

register/reg_file_tb.sv
`timescale 1ns/1ps // Define time units and resolution
`include "reg_file.sv" // Include all modules being used in this module

module reg_file_tb;
// address inputs
logic [3:0] RA1, RA2, WA; 
// data input
logic [7:0] ALUResult;
logic write_enable, CLK;
// outputs
logic [7:0] RD1,RD2,cpu_out;
reg_file dut (RA1,RA2,WA,ALUResult,write_enable,CLK,RD1,RD2,cpu_out); // Instantiate the module under test. dut (device
// under test) is the name we have chosen

initial begin // Single pass behaviour which starts at time 0 ns
$dumpfile("reg_file_tb.vcd"); // Dump variable changes in the vcd file
$dumpvars(0, reg_file_tb); // Specifies which variables to dump in the vcd file
//$display("this works");
$display("this is displayed here");

//write to registers 
for(int i = 1; i<16; i++)
    begin
        WA = i; CLK = 1; write_enable = 1; ALUResult = 4'd2; 
        #20; 
        CLK= 0; write_enable = 0; 
        #20;
    end 

// read from registers
RA1 = 1;
for(int i = 0; i<16; i++)
    begin 
        RA1 = i; RA2 = RA1;
        $display("time = %3d, RA1 = RA2 = %d, RD1 = RD2 = %d", $time, RA1, RD1);#20;
    end

end 

/*
// store data in reg 1 
CLK = 1; write_enable = 1;ALUResult = 00000001; WA = 0001; #20;
CLK = 0;  #20;
// store data in reg 2
CLK =1; write_enable = 1;ALUResult = 00000010; WA = 0010;
#20;
CLK = 0; 
#20;
// read data from reg 1 and 2 
CLK =1; write_enable = 0; RA1 = 0001; RA2 = 0010; 
#20;
CLK= 0; 
#20;
*/

endmodule

register/reg_file_tb.vcd
$date
	Mon Feb 12 16:02:48 2024
$end
$version
	Icarus Verilog
$end
$timescale
	1ps
$end
$scope module reg_file_tb $end
$var wire 8 ! cpu_out [7:0] $end
$var wire 8 " RD2 [7:0] $end
$var wire 8 # RD1 [7:0] $end
$var reg 8 $ ALUResult [7:0] $end
$var reg 1 % CLK $end
$var reg 4 & RA1 [3:0] $end
$var reg 4 ' RA2 [3:0] $end
$var reg 4 ( WA [3:0] $end
$var reg 1 ) write_enable $end
$scope module dut $end
$var wire 8 * ALUResult [7:0] $end
$var wire 1 % CLK $end
$var wire 4 + RA1 [3:0] $end
$var wire 4 , RA2 [3:0] $end
$var wire 8 - RD1 [7:0] $end
$var wire 8 . RD2 [7:0] $end
$var wire 4 / WA [3:0] $end
$var wire 8 0 cpu_out [7:0] $end
$var wire 1 ) write_enable $end
$upscope $end
$scope begin $ivl_for_loop0 $end
$var integer 32 1 i [31:0] $end
$upscope $end
$scope begin $ivl_for_loop1 $end
$var integer 32 2 i [31:0] $end
$upscope $end
$upscope $end
$enddefinitions $end
$comment Show the parameter values. $end
$dumpall
$end
#0
$dumpvars
b0 2
b1 1
bx 0
b1 /
bx .
bx -
bx ,
bx +
b10 *
1)
b1 (
bx '
bx &
1%
b10 $
bx #
bx "
bx !
$end
#20000
0)
0%
#40000
1)
1%
b10 (
b10 /
b10 1
#60000
0)
0%
#80000
1)
1%
b11 (
b11 /
b11 1
#100000
0)
0%
#120000
1)
1%
b100 (
b100 /
b100 1
#140000
0)
0%
#160000
1)
1%
b101 (
b101 /
b101 1
#180000
0)
0%
#200000
1)
1%
b110 (
b110 /
b110 1
#220000
0)
0%
#240000
1)
1%
b111 (
b111 /
b111 1
#260000
0)
0%
#280000
1)
1%
b1000 (
b1000 /
b1000 1
#300000
0)
0%
#320000
1)
1%
b1001 (
b1001 /
b1001 1
#340000
0)
0%
#360000
1)
1%
b1010 (
b1010 /
b1010 1
#380000
0)
0%
#400000
1)
1%
b1011 (
b1011 /
b1011 1
#420000
0)
0%
#440000
1)
1%
b1100 (
b1100 /
b1100 1
#460000
0)
0%
#480000
1)
1%
b1101 (
b1101 /
b1101 1
#500000
0)
0%
#520000
1)
1%
b1110 (
b1110 /
b1110 1
#540000
0)
0%
#560000
b10 !
b10 0
1)
1%
b1111 (
b1111 /
b1111 1
#580000
0)
0%
#600000
b0 "
b0 .
b0 '
b0 ,
b0 #
b0 -
b0 &
b0 +
b10000 1
#620000
b10 "
b10 .
b1 '
b1 ,
b10 #
b10 -
b1 &
b1 +
b1 2
#640000
b10 '
b10 ,
b10 &
b10 +
b10 2
#660000
b11 '
b11 ,
b11 &
b11 +
b11 2
#680000
b100 '
b100 ,
b100 &
b100 +
b100 2
#700000
b101 '
b101 ,
b101 &
b101 +
b101 2
#720000
b110 '
b110 ,
b110 &
b110 +
b110 2
#740000
b111 '
b111 ,
b111 &
b111 +
b111 2
#760000
b1000 '
b1000 ,
b1000 &
b1000 +
b1000 2
#780000
b1001 '
b1001 ,
b1001 &
b1001 +
b1001 2
#800000
b1010 '
b1010 ,
b1010 &
b1010 +
b1010 2
#820000
b1011 '
b1011 ,
b1011 &
b1011 +
b1011 2
#840000
b1100 '
b1100 ,
b1100 &
b1100 +
b1100 2
#860000
b1101 '
b1101 ,
b1101 &
b1101 +
b1101 2
#880000
b1110 '
b1110 ,
b1110 &
b1110 +
b1110 2
#900000
b1111 '
b1111 ,
b1111 &
b1111 +
b1111 2
#920000
b10000 2
