register/reg_file.sv
module reg_file (input logic [3:0] RA1, RA2, WA, 
                 input logic [7:0] ALUResult,
                 input logic write_enable,
                 input logic CLK,
                 output logic [7:0] RD1, RD2, cpu_out);

// define registers -> width of data -> number of addresses
reg [7:0] register [0:15];

//assign register[0] = 0; // set x0 to 0 

// continous assignment 
assign RD1 = register[RA1];
assign RD2 = register[RA2];
assign cpu_out = register[15];
//assign register[0] = 0;

always_ff @ (posedge CLK)
begin

// write to register at address given by WA
if(write_enable && (WA>0)) register[WA] <= ALUResult;
register[0] <= 0;

end

endmodule

reg_file_alu/reg_file_alu.sv
//`incdir "C:/Users/aleig/OneDrive - University College London/Documents/EEEYear2/ELEC0010/system_verilog_design/register/"

//`include "reg_file.sv"

//reg_file r0 (.RD1_wire(RD1))

module reg_file_alu (input logic [3:0] RA1, RA2, WA, 
                    input logic write_enable,CLK, ALUSrc, 
                    input logic [1:0] ALUControl,
                    input logic [7:0] immediate,
                    output logic Zero,
                    output logic [7:0] cpu_out,ALUResult);

// define registers -> width of data -> number of addresses
reg [7:0] register [0:15];
// define wires, outputs of register
logic [7:0] RD1 = (RA1 != 4'd0)? register[RA1]: 8'd0; // connect to module    
logic [7:0] RD2 = (RA2 != 4'd0)? register[RA2]: 8'd0; // connect to module
// select SrcB
logic [7:0] SrcB = (ALUSrc)? immediate : RD2; 
// assign cpu_out

assign cpu_out = register[15];


// register is clock run
always_ff @ (posedge CLK)
    begin
        // write to register at address given by WA
        if(write_enable && (WA>0)) register[WA] <= ALUResult;
        // register 0 is always 0
        //register[0] <= 0;
    end

// ALU is combinational 
always_comb 
    begin 
        
        
        // select ALU action
        case(ALUControl)
        // bitwise AND
        2'b00: ALUResult = (RD1 & SrcB); 
        // bitwise OR
        2'b01: ALUResult = (RD1 | SrcB); 
        // numerical addition 
        2'b10: ALUResult = (RD1 + SrcB); 
        // numerical subtraction
        2'b11: ALUResult = (RD1 - SrcB); 
        default: ALUResult = 8'bx;
        endcase
        
        // Zero output
        if (ALUResult == 0) Zero = 1;
            else Zero = 0;

    end

endmodule

instruction_memory_pc/instruction_memory_pc.sv
 module instruction_memory_pc(input logic [7:0] immediate,
                              input logic PCSrc,CLK,reset,
                              output logic [23:0] instr);


logic [23:0] data_ROM [0:255];
initial $readmemh("program.txt", data_ROM);
assign instr = data_ROM[PC];
logic [7:0] PC;



always_ff @ (posedge CLK) 
    begin
        if (reset) PC <= 8'd0;
        else PC <= (PCSrc)? immediate: PC + 8'd1;
    end
// try with out file 



endmodule

cu/cu.sv
module cu (input logic [3:0] opcode,
           output logic Branch, ALUSrc,RegWrite,
           output logic [1:0] ALUControl);

always_comb 
begin 

case(opcode) // switch case statement
//and
4'd0: 
    begin 
        RegWrite = 1; ALUSrc = 0; ALUControl = 2'b00; Branch = 0; 
    end  
//or
4'd1: 
    begin   
        RegWrite = 1; ALUSrc = 0; ALUControl = 2'b01; Branch = 0; 
    end
//add
4'd2:
    begin  
        RegWrite = 1; ALUSrc = 0; ALUControl = 2'b10; Branch = 0; 
    end
//sub
4'd3:
    begin
        RegWrite = 1; ALUSrc = 0; ALUControl = 2'b11; Branch = 0;
    end 
//andi
4'd4: 
    begin 
        RegWrite = 1; ALUSrc = 1; ALUControl = 2'b00; Branch = 0;
    end
//ori 
4'd5: 
    begin  
        RegWrite = 1; ALUSrc = 1; ALUControl = 2'b01; Branch = 0; 
    end
//addi
4'd6: 
    begin 
        RegWrite = 1; ALUSrc = 1; ALUControl = 2'b10; Branch = 0; 
    end
//beq
4'd7:
    begin 
        RegWrite = 0; ALUSrc = 0; ALUControl = 2'b11; Branch = 1; 
    end


endcase

end

endmodule

complete_cpu/cpu.sv
`include "../reg_file_alu/reg_file_alu.sv"
`include "../instruction_memory_pc/instruction_memory_pc.sv" 
`include "../cu/cu.sv" 

module cpu(input logic CLK,reset,
            output logic [7:0] ALUResult,
            output logic [7:0] cpu_out);

// control unit ports
logic [3:0] opcode;
logic Branch, ALUSrc, RegWrite;
logic [1:0] ALUControl;

// instantiate control unit
cu control_unit(.opcode(opcode),.Branch(Branch),.ALUSrc(ALUSrc),.RegWrite(RegWrite),.ALUControl(ALUControl));

//instruction memory ports
logic [7:0] immediate;
logic PCSrc;
logic [23:0] instr;

// intanitate inctruction memory pc
instruction_memory_pc memory(.immediate(immediate),.PCSrc(PCSrc),.CLK(CLK),.reset(reset),.instr(instr));

// register file ports
logic[3:0] RA1, RA2, WA;
logic write_enable, Zero;



// instantiate register file
reg_file_alu register(.RA1(RA1),.RA2(RA2),.WA(WA),.write_enable(write_enable),.CLK(CLK),.ALUSrc(ALUSrc),.ALUControl(ALUControl),.immediate(immediate),.Zero(Zero),.cpu_out(cpu_out),.ALUResult(ALUResult));  

//split up instr vector
assign opcode = instr[23:20];
assign WA = instr[19:16];
assign RA1 = instr[15:12];
assign RA2 = instr[11:8];
assign immediate = instr[7:0]; // Assign the correct range for immediate

// link outputs of control unit
assign write_enable = RegWrite;
//ALUSrc both have same name
//ALUcontrol both have same name



//outputs
// do i need to restate them?  

// PCSrc AND gate
always_comb
    begin 
        PCSrc = (Branch & Zero);
    end 



endmodule

complete_cpu/cpu_tb.sv
`timescale 1ns/1ps // Define time units and resolution
`include "cpu.sv" // Include all modules being used in this module

module cpu_tb;
logic CLK, reset;
logic [7:0] ALUResult,cpu_out;

cpu dut(CLK,reset,ALUResult,cpu_out); // Instantiate the module under test

initial begin // Single pass behaviour which starts at time 0 ns
$dumpfile("cpu_tb.vcd"); // Dump variable changes in the vcd file
$dumpvars(0, cpu_tb); // Specifies which variables to dump in the vcd file
$display("this works");

reset =1;  CLK = 0; #20; 
CLK=1; #20;
reset = 0; #20;

for(int i = 0; i<8;i++)
    begin 
        CLK = 0; #20;
        CLK = 1; #20;

    end

end


initial begin
$monitor("t = %3d,CLK = %b, reset = %b,ALUResult = %d, cpu_out = %d \n", $time, CLK, reset, ALUResult,cpu_out);
end // Print variable
// values on screen

endmodule

complete_cpu/cpu_tb.vcd
$date
	Tue Feb 13 19:47:13 2024
$end
$version
	Icarus Verilog
$end
$timescale
	1ps
$end
$scope module cpu_tb $end
$var wire 8 ! cpu_out [7:0] $end
$var wire 8 " ALUResult [7:0] $end
$var reg 1 # CLK $end
$var reg 1 $ reset $end
$scope module dut $end
$var wire 1 # CLK $end
$var wire 1 $ reset $end
$var wire 1 % write_enable $end
$var wire 4 & opcode [3:0] $end
$var wire 24 ' instr [23:0] $end
$var wire 8 ( immediate [7:0] $end
$var wire 8 ) cpu_out [7:0] $end
$var wire 1 * Zero $end
$var wire 4 + WA [3:0] $end
$var wire 1 , RegWrite $end
$var wire 4 - RA2 [3:0] $end
$var wire 4 . RA1 [3:0] $end
$var wire 1 / Branch $end
$var wire 1 0 ALUSrc $end
$var wire 8 1 ALUResult [7:0] $end
$var wire 2 2 ALUControl [1:0] $end
$var reg 1 3 PCSrc $end
$scope module control_unit $end
$var wire 4 4 opcode [3:0] $end
$var reg 2 5 ALUControl [1:0] $end
$var reg 1 0 ALUSrc $end
$var reg 1 / Branch $end
$var reg 1 , RegWrite $end
$upscope $end
$scope module memory $end
$var wire 1 # CLK $end
$var wire 1 3 PCSrc $end
$var wire 8 6 immediate [7:0] $end
$var wire 24 7 instr [23:0] $end
$var wire 1 $ reset $end
$var reg 8 8 PC [7:0] $end
$upscope $end
$scope module register $end
$var wire 2 9 ALUControl [1:0] $end
$var wire 1 0 ALUSrc $end
$var wire 1 # CLK $end
$var wire 4 : RA1 [3:0] $end
$var wire 4 ; RA2 [3:0] $end
$var wire 4 < WA [3:0] $end
$var wire 8 = cpu_out [7:0] $end
$var wire 8 > immediate [7:0] $end
$var wire 1 % write_enable $end
$var reg 8 ? ALUResult [7:0] $end
$var reg 8 @ RD1 [7:0] $end
$var reg 8 A RD2 [7:0] $end
$var reg 8 B SrcB [7:0] $end
$var reg 1 * Zero $end
$upscope $end
$upscope $end
$scope begin $ivl_for_loop0 $end
$var integer 32 C i [31:0] $end
$upscope $end
$upscope $end
$enddefinitions $end
$comment Show the parameter values. $end
$dumpall
$end
#0
$dumpvars
b0 C
bx B
bx A
bx @
bx ?
bx >
bx =
bx <
bx ;
bx :
bx 9
bx 8
bx 7
bx 6
bx 5
bx 4
03
bx 2
bx 1
x0
x/
bx .
bx -
x,
bx +
0*
bx )
bx (
bx '
bx &
x%
1$
0#
bx "
bx !
$end
#20000
0/
b10 2
b10 5
b10 9
10
1%
1,
b1 (
b1 6
b1 >
b0 -
b0 ;
b0 .
b0 :
b1 +
b1 <
b110 &
b110 4
b11000010000000000000001 '
b11000010000000000000001 7
b0 8
1#
#40000
0$
#60000
0#
#80000
b100000 (
b100000 6
b100000 >
b10 +
b10 <
b11000100000000000100000 '
b11000100000000000100000 7
b1 8
1#
#100000
0#
b1 C
#120000
b0 (
b0 6
b0 >
b1111 +
b1111 <
b11011110000000000000000 '
b11011110000000000000000 7
b10 8
1#
#140000
0#
b10 C
#160000
1/
b11 2
b11 5
b11 9
00
0%
0,
b111 (
b111 6
b111 >
b10 -
b10 ;
b1 .
b1 :
b0 +
b0 <
b111 &
b111 4
b11100000001001000000111 '
b11100000001001000000111 7
b11 8
1#
#180000
0#
b11 C
#200000
0/
b10 2
b10 5
b10 9
1%
1,
b0 (
b0 6
b0 >
b1 -
b1 ;
b1 +
b1 <
b10 &
b10 4
b1000010001000100000000 '
b1000010001000100000000 7
b100 8
1#
#220000
0#
b100 C
#240000
10
b1 (
b1 6
b1 >
b0 -
b0 ;
b1111 .
b1111 :
b1111 +
b1111 <
b110 &
b110 4
b11011111111000000000001 '
b11011111111000000000001 7
b101 8
1#
#260000
0#
b101 C
#280000
1/
b11 2
b11 5
b11 9
00
0%
0,
b11 (
b11 6
b11 >
b0 .
b0 :
b0 +
b0 <
b111 &
b111 4
b11100000000000000000011 '
b11100000000000000000011 7
b110 8
1#
#300000
0#
b110 C
#320000
b111 (
b111 6
b111 >
b11100000000000000000111 '
b11100000000000000000111 7
b111 8
1#
#340000
0#
b111 C
#360000
bx (
bx 6
bx >
bx -
bx ;
bx .
bx :
bx +
bx <
bx &
bx 4
bx '
bx 7
b1000 8
1#
#380000
b1000 C
