reg_file_alu/reg_file_alu.sv
module reg_file_alu (input logic [3:0] RA1, RA2, WA, 
                    input logic write_enable,CLK, ALUSrc, 
                    input logic [1:0] ALUControl,
                    input logic [7:0] immediate,
                    output logic Zero,
                    output logic [7:0] cpu_out,ALUResult);

// define registers -> width of data -> number of addresses
reg [7:0] register [0:15];
// define read datas
logic [7:0] RD1;  
logic [7:0] RD2;
// define SrcB
logic [7:0] SrcB; 
// define reg0
//reg register[0] = 0;


// assignments, these output 0 if register 0 is called

assign RD1 = (RA1 != 4'd0)? register[RA1]: 8'd0;
assign RD2 = (RA2 != 4'd0)? register[RA2]: 8'd0;
assign SrcB = (ALUSrc)? immediate : RD2; 
assign cpu_out = register[15];
//assign register[0] = 0;


// register is clock run
always_ff @ (posedge CLK)
    begin
        // write to register at address given by WA
        if(write_enable && (WA>0)) register[WA] <= ALUResult;
        // register 0 is always 0
        //register[0] <= 0;
    end

// ALU is combinational 
always_comb 
    begin 
        // select ALU action
        case(ALUControl)
        // bitwise AND
        2'b00: ALUResult = (RD1 & SrcB); 
        // bitwise OR
        2'b01: ALUResult = (RD1 | SrcB); 
        // numerical addition 
        2'b10: ALUResult = (RD1 + SrcB); 
        // numerical subtraction
        2'b11: ALUResult = (RD1 - SrcB); 
        default: ALUResult = 8'bx;
        endcase
        
        // Zero output
        if (ALUResult == 0) Zero = 1;
            else Zero = 0;

    end

endmodule

instruction_memory_pc/instruction_memory_pc.sv
 module instruction_memory_pc(input logic [7:0] immediate,
                              input logic PCSrc,CLK,reset,
                              output logic [23:0] instr);


logic [23:0] data_ROM [0:255];
initial $readmemh("program.txt", data_ROM);
assign instr = data_ROM[PC];
logic [7:0] PC;



always_ff @ (posedge CLK) 
    begin
        if (reset) PC <= 8'd0;
        else PC <= (PCSrc)? immediate: PC + 8'd1;
    end
// try with out file 



endmodule

cu/cu.sv
module cu (input logic [3:0] opcode,
           output logic Branch, ALUSrc,RegWrite,
           output logic [1:0] ALUControl);

always_comb 
begin 

case(opcode) // switch case statement
//and
4'd0: 
    begin 
        RegWrite = 1; ALUSrc = 0; ALUControl = 2'b00; Branch = 0; 
    end  
//or
4'd1: 
    begin   
        RegWrite = 1; ALUSrc = 0; ALUControl = 2'b01; Branch = 0; 
    end
//add
4'd2:
    begin  
        RegWrite = 1; ALUSrc = 0; ALUControl = 2'b10; Branch = 0; 
    end
//sub
4'd3:
    begin
        RegWrite = 1; ALUSrc = 0; ALUControl = 2'b11; Branch = 0;
    end 
//andi
4'd4: 
    begin 
        RegWrite = 1; ALUSrc = 1; ALUControl = 2'b00; Branch = 0;
    end
//ori 
4'd5: 
    begin  
        RegWrite = 1; ALUSrc = 1; ALUControl = 2'b01; Branch = 0; 
    end
//addi
4'd6: 
    begin 
        RegWrite = 1; ALUSrc = 1; ALUControl = 2'b10; Branch = 0; 
    end
//beq
4'd7:
    begin 
        RegWrite = 0; ALUSrc = 0; ALUControl = 2'b11; Branch = 1; 
    end


endcase

end

endmodule

complete_cpu/cpu.sv
`include "../reg_file_alu/reg_file_alu.sv"
`include "../instruction_memory_pc/instruction_memory_pc.sv" 
`include "../cu/cu.sv" 

module cpu(input logic CLK,reset,
            output logic [7:0] ALUResult,
            output logic [7:0] cpu_out,
            output logic [23:0] instr);

// control unit ports
logic [3:0] opcode;
logic Branch, ALUSrc, RegWrite;
logic [1:0] ALUControl;

// instantiate control unit
cu control_unit(.opcode(opcode),.Branch(Branch),.ALUSrc(ALUSrc),.RegWrite(RegWrite),.ALUControl(ALUControl));

//instruction memory ports
logic [7:0] immediate;
logic PCSrc;
//logic [23:0] instr;

// intanitate inctruction memory pc
instruction_memory_pc memory(.immediate(immediate),.PCSrc(PCSrc),.CLK(CLK),.reset(reset),.instr(instr));

// register file ports
logic[3:0] RA1, RA2, WA;
logic write_enable, Zero;

// instantiate register file
reg_file_alu register(.RA1(RA1),.RA2(RA2),.WA(WA),.write_enable(write_enable),.CLK(CLK),.ALUSrc(ALUSrc),.ALUControl(ALUControl),.immediate(immediate),.Zero(Zero),.cpu_out(cpu_out),.ALUResult(ALUResult));  

//split up instr vector
assign opcode = instr[23:20];
assign WA = instr[19:16];
assign RA1 = instr[15:12];
assign RA2 = instr[11:8];
assign immediate = instr[7:0]; // Assign the correct range for immediate

// link outputs of control unit
assign write_enable = RegWrite;
//ALUSrc both have same name
//ALUcontrol both have same name



//outputs
// do i need to restate them?  

// PCSrc AND gate
always_comb
    begin 
        PCSrc = (Branch & Zero);
    end 



endmodule

complete_cpu/cpu_tb.sv
`timescale 1ns/1ps // Define time units and resolution
`include "cpu.sv" // Include all modules being used in this module

module cpu_tb;
logic CLK, reset;
logic [7:0] ALUResult,cpu_out;
logic [23:0] instr;

cpu dut(CLK,reset,ALUResult,cpu_out,instr); // Instantiate the module under test

initial begin // Single pass behaviour which starts at time 0 ns
$dumpfile("cpu_tb.vcd"); // Dump variable changes in the vcd file
$dumpvars(0, cpu_tb); // Specifies which variables to dump in the vcd file
$display("this works");

CLK =1; reset =1; #20; 

reset = 0; #20;

for(int i = 0; i< 100;i++)
    begin 
        CLK = 0; #20;
        CLK = 1; #20;

    end

end


initial begin
$monitor("t = %3d,CLK = %b, reset = %b, instr = %h,ALUResult = %d, cpu_out = %d \n", $time, CLK, reset, instr, ALUResult,cpu_out);
end // Print variable
// values on screen

endmodule

complete_cpu/cpu_tb.vcd
$date
	Wed Feb 14 16:17:11 2024
$end
$version
	Icarus Verilog
$end
$timescale
	1ps
$end
$scope module cpu_tb $end
$var wire 24 ! instr [23:0] $end
$var wire 8 " cpu_out [7:0] $end
$var wire 8 # ALUResult [7:0] $end
$var reg 1 $ CLK $end
$var reg 1 % reset $end
$scope module dut $end
$var wire 1 $ CLK $end
$var wire 1 % reset $end
$var wire 1 & write_enable $end
$var wire 4 ' opcode [3:0] $end
$var wire 24 ( instr [23:0] $end
$var wire 8 ) immediate [7:0] $end
$var wire 8 * cpu_out [7:0] $end
$var wire 1 + Zero $end
$var wire 4 , WA [3:0] $end
$var wire 1 - RegWrite $end
$var wire 4 . RA2 [3:0] $end
$var wire 4 / RA1 [3:0] $end
$var wire 1 0 Branch $end
$var wire 1 1 ALUSrc $end
$var wire 8 2 ALUResult [7:0] $end
$var wire 2 3 ALUControl [1:0] $end
$var reg 1 4 PCSrc $end
$scope module control_unit $end
$var wire 4 5 opcode [3:0] $end
$var reg 2 6 ALUControl [1:0] $end
$var reg 1 1 ALUSrc $end
$var reg 1 0 Branch $end
$var reg 1 - RegWrite $end
$upscope $end
$scope module memory $end
$var wire 1 $ CLK $end
$var wire 1 4 PCSrc $end
$var wire 8 7 immediate [7:0] $end
$var wire 24 8 instr [23:0] $end
$var wire 1 % reset $end
$var reg 8 9 PC [7:0] $end
$upscope $end
$scope module register $end
$var wire 2 : ALUControl [1:0] $end
$var wire 1 1 ALUSrc $end
$var wire 1 $ CLK $end
$var wire 4 ; RA1 [3:0] $end
$var wire 4 < RA2 [3:0] $end
$var wire 4 = WA [3:0] $end
$var wire 8 > cpu_out [7:0] $end
$var wire 8 ? immediate [7:0] $end
$var wire 1 & write_enable $end
$var wire 8 @ SrcB [7:0] $end
$var wire 8 A RD2 [7:0] $end
$var wire 8 B RD1 [7:0] $end
$var reg 8 C ALUResult [7:0] $end
$var reg 1 + Zero $end
$upscope $end
$upscope $end
$scope begin $ivl_for_loop0 $end
$var integer 32 D i [31:0] $end
$upscope $end
$upscope $end
$enddefinitions $end
$comment Show the parameter values. $end
$dumpall
$end
#0
$dumpvars
b0 D
b1 C
b0 B
b0 A
b1 @
b1 ?
bx >
b1 =
b0 <
b0 ;
b10 :
b0 9
b11000010000000000000001 8
b1 7
b10 6
b110 5
04
b10 3
b1 2
11
00
b0 /
b0 .
1-
b1 ,
0+
bx *
b1 )
b11000010000000000000001 (
b110 '
1&
1%
1$
b1 #
bx "
b11000010000000000000001 !
$end
#20000
0%
#40000
0$
#60000
b100000 #
b100000 2
b100000 C
b100000 @
b100000 )
b100000 7
b100000 ?
b10 ,
b10 =
b11000100000000000100000 !
b11000100000000000100000 (
b11000100000000000100000 8
b1 9
1$
#80000
0$
b1 D
#100000
1+
b0 #
b0 2
b0 C
b0 @
b0 )
b0 7
b0 ?
b1111 ,
b1111 =
b11011110000000000000000 !
b11011110000000000000000 (
b11011110000000000000000 8
b10 9
1$
#120000
0$
b10 D
#140000
0+
b11100001 #
b11100001 2
b11100001 C
b100000 @
b100000 A
b1 B
10
b11 3
b11 6
b11 :
01
0&
0-
b111 )
b111 7
b111 ?
b10 .
b10 <
b1 /
b1 ;
b0 ,
b0 =
b111 '
b111 5
b0 "
b0 *
b0 >
b11100000001001000000111 !
b11100000001001000000111 (
b11100000001001000000111 8
b11 9
1$
#160000
0$
b11 D
#180000
b1 @
b10 #
b10 2
b10 C
b1 A
00
b10 3
b10 6
b10 :
1&
1-
b0 )
b0 7
b0 ?
b1 .
b1 <
b1 ,
b1 =
b10 '
b10 5
b1000010001000100000000 !
b1000010001000100000000 (
b1000010001000100000000 8
b100 9
1$
#200000
0$
b100 D
#220000
b1 #
b1 2
b1 C
11
b0 B
b0 A
b1 )
b1 7
b1 ?
b0 .
b0 <
b1111 /
b1111 ;
b1111 ,
b1111 =
b110 '
b110 5
b11011111111000000000001 !
b11011111111000000000001 (
b11011111111000000000001 8
b101 9
1$
#240000
0$
b101 D
#260000
14
1+
b0 @
10
b11 3
b11 6
b11 :
01
0&
0-
b0 #
b0 2
b0 C
b11 )
b11 7
b11 ?
b0 /
b0 ;
b0 ,
b0 =
b111 '
b111 5
b0 B
b11100000000000000000011 !
b11100000000000000000011 (
b11100000000000000000011 8
b110 9
b1 "
b1 *
b1 >
1$
#280000
0$
b110 D
#300000
04
b100000 @
0+
b11100010 #
b11100010 2
b11100010 C
b100000 A
b10 B
b111 )
b111 7
b111 ?
b10 .
b10 <
b1 /
b1 ;
b11100000001001000000111 !
b11100000001001000000111 (
b11100000001001000000111 8
b11 9
1$
#320000
0$
b111 D
#340000
b10 @
b100 #
b100 2
b100 C
b10 A
00
b10 3
b10 6
b10 :
1&
1-
b0 )
b0 7
b0 ?
b1 .
b1 <
b1 ,
b1 =
b10 '
b10 5
b1000010001000100000000 !
b1000010001000100000000 (
b1000010001000100000000 8
b100 9
1$
#360000
0$
b1000 D
#380000
b10 #
b10 2
b10 C
b1 @
11
b1 B
b0 A
b1 )
b1 7
b1 ?
b0 .
b0 <
b1111 /
b1111 ;
b1111 ,
b1111 =
b110 '
b110 5
b11011111111000000000001 !
b11011111111000000000001 (
b11011111111000000000001 8
b101 9
1$
#400000
0$
b1001 D
#420000
14
1+
b0 @
10
b11 3
b11 6
b11 :
01
0&
0-
b0 #
b0 2
b0 C
b11 )
b11 7
b11 ?
b0 /
b0 ;
b0 ,
b0 =
b111 '
b111 5
b0 B
b11100000000000000000011 !
b11100000000000000000011 (
b11100000000000000000011 8
b110 9
b10 "
b10 *
b10 >
1$
#440000
0$
b1010 D
#460000
04
b100000 @
0+
b11100100 #
b11100100 2
b11100100 C
b100000 A
b100 B
b111 )
b111 7
b111 ?
b10 .
b10 <
b1 /
b1 ;
b11100000001001000000111 !
b11100000001001000000111 (
b11100000001001000000111 8
b11 9
1$
#480000
0$
b1011 D
#500000
b100 @
b1000 #
b1000 2
b1000 C
b100 A
00
b10 3
b10 6
b10 :
1&
1-
b0 )
b0 7
b0 ?
b1 .
b1 <
b1 ,
b1 =
b10 '
b10 5
b1000010001000100000000 !
b1000010001000100000000 (
b1000010001000100000000 8
b100 9
1$
#520000
0$
b1100 D
#540000
b11 #
b11 2
b11 C
b1 @
11
b10 B
b0 A
b1 )
b1 7
b1 ?
b0 .
b0 <
b1111 /
b1111 ;
b1111 ,
b1111 =
b110 '
b110 5
b11011111111000000000001 !
b11011111111000000000001 (
b11011111111000000000001 8
b101 9
1$
#560000
0$
b1101 D
#580000
14
1+
b0 @
10
b11 3
b11 6
b11 :
01
0&
0-
b0 #
b0 2
b0 C
b11 )
b11 7
b11 ?
b0 /
b0 ;
b0 ,
b0 =
b111 '
b111 5
b0 B
b11100000000000000000011 !
b11100000000000000000011 (
b11100000000000000000011 8
b110 9
b11 "
b11 *
b11 >
1$
#600000
0$
b1110 D
#620000
04
b100000 @
0+
b11101000 #
b11101000 2
b11101000 C
b100000 A
b1000 B
b111 )
b111 7
b111 ?
b10 .
b10 <
b1 /
b1 ;
b11100000001001000000111 !
b11100000001001000000111 (
b11100000001001000000111 8
b11 9
1$
#640000
0$
b1111 D
#660000
b1000 @
b10000 #
b10000 2
b10000 C
b1000 A
00
b10 3
b10 6
b10 :
1&
1-
b0 )
b0 7
b0 ?
b1 .
b1 <
b1 ,
b1 =
b10 '
b10 5
b1000010001000100000000 !
b1000010001000100000000 (
b1000010001000100000000 8
b100 9
1$
#680000
0$
b10000 D
#700000
b100 #
b100 2
b100 C
b1 @
11
b11 B
b0 A
b1 )
b1 7
b1 ?
b0 .
b0 <
b1111 /
b1111 ;
b1111 ,
b1111 =
b110 '
b110 5
b11011111111000000000001 !
b11011111111000000000001 (
b11011111111000000000001 8
b101 9
1$
#720000
0$
b10001 D
#740000
14
1+
b0 @
10
b11 3
b11 6
b11 :
01
0&
0-
b0 #
b0 2
b0 C
b11 )
b11 7
b11 ?
b0 /
b0 ;
b0 ,
b0 =
b111 '
b111 5
b0 B
b11100000000000000000011 !
b11100000000000000000011 (
b11100000000000000000011 8
b110 9
b100 "
b100 *
b100 >
1$
#760000
0$
b10010 D
#780000
04
b100000 @
0+
b11110000 #
b11110000 2
b11110000 C
b100000 A
b10000 B
b111 )
b111 7
b111 ?
b10 .
b10 <
b1 /
b1 ;
b11100000001001000000111 !
b11100000001001000000111 (
b11100000001001000000111 8
b11 9
1$
#800000
0$
b10011 D
#820000
b10000 @
b100000 #
b100000 2
b100000 C
b10000 A
00
b10 3
b10 6
b10 :
1&
1-
b0 )
b0 7
b0 ?
b1 .
b1 <
b1 ,
b1 =
b10 '
b10 5
b1000010001000100000000 !
b1000010001000100000000 (
b1000010001000100000000 8
b100 9
1$
#840000
0$
b10100 D
#860000
b101 #
b101 2
b101 C
b1 @
11
b100 B
b0 A
b1 )
b1 7
b1 ?
b0 .
b0 <
b1111 /
b1111 ;
b1111 ,
b1111 =
b110 '
b110 5
b11011111111000000000001 !
b11011111111000000000001 (
b11011111111000000000001 8
b101 9
1$
#880000
0$
b10101 D
#900000
14
1+
b0 @
10
b11 3
b11 6
b11 :
01
0&
0-
b0 #
b0 2
b0 C
b11 )
b11 7
b11 ?
b0 /
b0 ;
b0 ,
b0 =
b111 '
b111 5
b0 B
b11100000000000000000011 !
b11100000000000000000011 (
b11100000000000000000011 8
b110 9
b101 "
b101 *
b101 >
1$
#920000
0$
b10110 D
#940000
14
b100000 @
1+
b0 #
b0 2
b0 C
b100000 A
b100000 B
b111 )
b111 7
b111 ?
b10 .
b10 <
b1 /
b1 ;
b11100000001001000000111 !
b11100000001001000000111 (
b11100000001001000000111 8
b11 9
1$
#960000
0$
b10111 D
#980000
14
b0 @
1+
b0 #
b0 2
b0 C
b0 A
b0 B
b0 .
b0 <
b0 /
b0 ;
b11100000000000000000111 !
b11100000000000000000111 (
b11100000000000000000111 8
b111 9
1$
#1000000
0$
b11000 D
#1020000
1$
#1040000
0$
b11001 D
#1060000
1$
#1080000
0$
b11010 D
#1100000
1$
#1120000
0$
b11011 D
#1140000
1$
#1160000
0$
b11100 D
#1180000
1$
#1200000
0$
b11101 D
#1220000
1$
#1240000
0$
b11110 D
#1260000
1$
#1280000
0$
b11111 D
#1300000
1$
#1320000
0$
b100000 D
#1340000
1$
#1360000
0$
b100001 D
#1380000
1$
#1400000
0$
b100010 D
#1420000
1$
#1440000
0$
b100011 D
#1460000
1$
#1480000
0$
b100100 D
#1500000
1$
#1520000
0$
b100101 D
#1540000
1$
#1560000
0$
b100110 D
#1580000
1$
#1600000
0$
b100111 D
#1620000
1$
#1640000
0$
b101000 D
#1660000
1$
#1680000
0$
b101001 D
#1700000
1$
#1720000
0$
b101010 D
#1740000
1$
#1760000
0$
b101011 D
#1780000
1$
#1800000
0$
b101100 D
#1820000
1$
#1840000
0$
b101101 D
#1860000
1$
#1880000
0$
b101110 D
#1900000
1$
#1920000
0$
b101111 D
#1940000
1$
#1960000
0$
b110000 D
#1980000
1$
#2000000
0$
b110001 D
#2020000
1$
#2040000
0$
b110010 D
#2060000
1$
#2080000
0$
b110011 D
#2100000
1$
#2120000
0$
b110100 D
#2140000
1$
#2160000
0$
b110101 D
#2180000
1$
#2200000
0$
b110110 D
#2220000
1$
#2240000
0$
b110111 D
#2260000
1$
#2280000
0$
b111000 D
#2300000
1$
#2320000
0$
b111001 D
#2340000
1$
#2360000
0$
b111010 D
#2380000
1$
#2400000
0$
b111011 D
#2420000
1$
#2440000
0$
b111100 D
#2460000
1$
#2480000
0$
b111101 D
#2500000
1$
#2520000
0$
b111110 D
#2540000
1$
#2560000
0$
b111111 D
#2580000
1$
#2600000
0$
b1000000 D
#2620000
1$
#2640000
0$
b1000001 D
#2660000
1$
#2680000
0$
b1000010 D
#2700000
1$
#2720000
0$
b1000011 D
#2740000
1$
#2760000
0$
b1000100 D
#2780000
1$
#2800000
0$
b1000101 D
#2820000
1$
#2840000
0$
b1000110 D
#2860000
1$
#2880000
0$
b1000111 D
#2900000
1$
#2920000
0$
b1001000 D
#2940000
1$
#2960000
0$
b1001001 D
#2980000
1$
#3000000
0$
b1001010 D
#3020000
1$
#3040000
0$
b1001011 D
#3060000
1$
#3080000
0$
b1001100 D
#3100000
1$
#3120000
0$
b1001101 D
#3140000
1$
#3160000
0$
b1001110 D
#3180000
1$
#3200000
0$
b1001111 D
#3220000
1$
#3240000
0$
b1010000 D
#3260000
1$
#3280000
0$
b1010001 D
#3300000
1$
#3320000
0$
b1010010 D
#3340000
1$
#3360000
0$
b1010011 D
#3380000
1$
#3400000
0$
b1010100 D
#3420000
1$
#3440000
0$
b1010101 D
#3460000
1$
#3480000
0$
b1010110 D
#3500000
1$
#3520000
0$
b1010111 D
#3540000
1$
#3560000
0$
b1011000 D
#3580000
1$
#3600000
0$
b1011001 D
#3620000
1$
#3640000
0$
b1011010 D
#3660000
1$
#3680000
0$
b1011011 D
#3700000
1$
#3720000
0$
b1011100 D
#3740000
1$
#3760000
0$
b1011101 D
#3780000
1$
#3800000
0$
b1011110 D
#3820000
1$
#3840000
0$
b1011111 D
#3860000
1$
#3880000
0$
b1100000 D
#3900000
1$
#3920000
0$
b1100001 D
#3940000
1$
#3960000
0$
b1100010 D
#3980000
1$
#4000000
0$
b1100011 D
#4020000
1$
#4040000
b1100100 D
