cu/cu.sv
module cu (input logic [3:0] opcode,
           output logic Branch, ALUSrc,RegWrite,
           output logic [1:0] ALUControl);

always_comb 
begin 

case(opcode) // switch case statement
//and
4'd0: 
    begin 
        RegWrite = 1; ALUSrc = 0; ALUControl = 2'b00; Branch = 0; 
    end  
//or
4'd1: 
    begin   
        RegWrite = 1; ALUSrc = 0; ALUControl = 2'b01; Branch = 0; 
    end
//add
4'd2:
    begin  
        RegWrite = 1; ALUSrc = 0; ALUControl = 2'b10; Branch = 0; 
    end
//sub
4'd3:
    begin
        RegWrite = 1; ALUSrc = 0; ALUControl = 2'b11; Branch = 0;
    end 
//andi
4'd4: 
    begin 
        RegWrite = 1; ALUSrc = 1; ALUControl = 2'b00; Branch = 0;
    end
//ori 
4'd5: 
    begin  
        RegWrite = 1; ALUSrc = 1; ALUControl = 2'b01; Branch = 0; 
    end
//addi
4'd6: 
    begin 
        RegWrite = 1; ALUSrc = 1; ALUControl = 2'b10; Branch = 0; 
    end
//beq
4'd7:
    begin 
        RegWrite = 0; ALUSrc = 0; ALUControl = 2'b11; Branch = 1; 
    end


endcase

end

endmodule

cu/cu_tb.sv
`timescale 1ns/1ps // Define time units and resolution
`include "cu.sv" // Include all modules being used in this module

module cu_tb;

logic [3:0] opcode;
logic [1:0] ALUControl;
logic Branch,ALUSrc,RegWrite;
cu dut(opcode,Branch,ALUSrc,RegWrite,ALUControl); 

initial begin // Single pass behaviour which starts at time 0 ns
$dumpfile("cu_tb.vcd"); // Dump variable changes in the vcd file
$dumpvars(0, cu_tb); // Specifies which variables to dump in the vcd file


// count up to 10
for (int i = 0; i<8; i++)
    begin
    opcode = i; #20;
    end
end 

initial begin // Single pass behaviour which starts at time 0 ns

$monitor("t = %3d, opcode = %d, RegWrite = %b, ALUSrc = %b, ALUControl = %b, Branch = %b \n", $time, opcode,RegWrite,ALUSrc,ALUControl,Branch);
end // Print variable

endmodule

cu/cu_tb.vcd
$date
	Mon Feb 12 18:11:50 2024
$end
$version
	Icarus Verilog
$end
$timescale
	1ps
$end
$scope module cu_tb $end
$var wire 1 ! RegWrite $end
$var wire 1 " Branch $end
$var wire 1 # ALUSrc $end
$var wire 2 $ ALUControl [1:0] $end
$var reg 4 % opcode [3:0] $end
$scope module dut $end
$var wire 4 & opcode [3:0] $end
$var reg 2 ' ALUControl [1:0] $end
$var reg 1 # ALUSrc $end
$var reg 1 " Branch $end
$var reg 1 ! RegWrite $end
$upscope $end
$scope begin $ivl_for_loop0 $end
$var integer 32 ( i [31:0] $end
$upscope $end
$upscope $end
$enddefinitions $end
$comment Show the parameter values. $end
$dumpall
$end
#0
$dumpvars
b0 (
b0 '
b0 &
b0 %
b0 $
0#
0"
1!
$end
#20000
b1 $
b1 '
b1 %
b1 &
b1 (
#40000
b10 $
b10 '
b10 %
b10 &
b10 (
#60000
b11 $
b11 '
b11 %
b11 &
b11 (
#80000
b0 $
b0 '
1#
b100 %
b100 &
b100 (
#100000
b1 $
b1 '
b101 %
b101 &
b101 (
#120000
b10 $
b10 '
b110 %
b110 &
b110 (
#140000
1"
b11 $
b11 '
0#
0!
b111 %
b111 &
b111 (
#160000
b1000 (
