register/reg_file.sv
module reg_file (input logic [3:0] RA1, RA2, WA, 
                 input logic [7:0] ALUResult,
                 input logic write_enable,
                 input logic CLK,
                 output logic [7:0] RD1, RD2, cpu_out);

// define registers -> width of data -> number of addresses
reg [7:0] register [0:15];

//assign register[0] = 0; // set x0 to 0 

// continous assignment 
assign RD1 = register[RA1];
assign RD2 = register[RA2];
assign cpu_out = register[15];
//assign register[0] = 0;

always_ff @ (posedge CLK)
begin

// write to register at address given by WA
if(write_enable && (WA>0)) register[WA] <= ALUResult;
register[0] <= 0;

end

endmodule

reg_file_alu/reg_file_alu.sv
//`incdir "C:/Users/aleig/OneDrive - University College London/Documents/EEEYear2/ELEC0010/system_verilog_design/register/"

//`include "reg_file.sv"

//reg_file r0 (.RD1_wire(RD1))

module reg_file_alu (input logic [3:0] RA1, RA2, WA, 
                    input logic write_enable,CLK, ALUSrc, 
                    input logic [1:0] ALUControl,
                    input logic [7:0] immediate,
                    output logic Zero,
                    output logic [7:0] cpu_out,ALUResult);

// define registers -> width of data -> number of addresses
reg [7:0] register [0:15];
// define wires, outputs of register
logic [7:0] RD1 = (RA1 != 4'd0)? register[RA1]: 8'd0; // connect to module    
logic [7:0] RD2 = (RA2 != 4'd0)? register[RA2]: 8'd0; // connect to module
// select SrcB
logic [7:0] SrcB = (ALUSrc)? immediate : RD2; 
// assign cpu_out

assign cpu_out = register[15];


// register is clock run
always_ff @ (posedge CLK)
    begin
        // write to register at address given by WA
        if(write_enable && (WA>0)) register[WA] <= ALUResult;
        // register 0 is always 0
        //register[0] <= 0;
    end

// ALU is combinational 
always_comb 
    begin 
        
        
        // select ALU action
        case(ALUControl)
        // bitwise AND
        2'b00: ALUResult = (RD1 & SrcB); 
        // bitwise OR
        2'b01: ALUResult = (RD1 | SrcB); 
        // numerical addition 
        2'b10: ALUResult = (RD1 + SrcB); 
        // numerical subtraction
        2'b11: ALUResult = (RD1 - SrcB); 
        default: ALUResult = 8'bx;
        endcase
        
        // Zero output
        if (ALUResult == 0) Zero = 1;
            else Zero = 0;

    end

endmodule

reg_file_alu/reg_file_alu_tb.sv
`timescale 1ns/1ps // Define time units and resolution
`include "reg_file_alu.sv" // Include all modules being used in this module

module reg_file_alu_tb;
// address inputs
logic [3:0] RA1, RA2, WA; 
logic write_enable,CLK, ALUSrc;
logic [1:0] ALUControl;
logic [7:0] immediate;
logic Zero;
logic [7:0] cpu_out,ALUResult;

reg_file_alu dut (RA1,RA2,WA,write_enable,CLK,ALUSrc,ALUControl,immediate,Zero,cpu_out,ALUResult); // Instantiate the module under test.

initial begin // Single pass behaviour which starts at time 0 ns
$dumpfile("reg_file_alu_tb.vcd"); // Dump variable changes in the vcd file
$dumpvars(0, reg_file_alu_tb); // Specifies which variables to dump in the vcd file


// read x0 
/*

CLK = 0; #20

CLK =1; RA1 = 0; ALUSrc =1; immediate = 8'd0; ALUControl = 2'b10; #20;

end

initial begin 
$monitor("time = %3d, CLK = %d, ALUResult = %d", $time, CLK,ALUResult);
end
*/



//writes i++ to all registers, ALU performs add, s
for(int i = 4'd1; i<16; i++)
    begin
        CLK=0; write_enable = 1; WA = i;  RA1 = 4'd0;  immediate = i; ALUSrc = 1; ALUControl = 2'b10;
        #20; 
        CLK= 1;  
        #20;

    end 



// read from registers, value RD1 register is added to 0. ALUResult is output from RD1
for(int i = 4'd0; i<16; i++)
    begin 
        write_enable = 0; RA1 = i; RA2 = RA1; ALUSrc =1; immediate = 8'b00000000; ALUControl = 2'b10;
        //$display("time = %3d, RA1 = RA2 = %d, ALUResult = %d", $time, RA1, ALUResult);
        #20;
    end

end


initial
 begin 
    $monitor("time = %3d, CLK = %d, write_enable= %b, WA = %d, RA1 = %d, ALUResult = %d, cpu_out = %d", $time, CLK, write_enable, WA, RA1, ALUResult,cpu_out);
end

endmodule

reg_file_alu/reg_file_alu_tb.vcd
$date
	Tue Feb 13 16:24:29 2024
$end
$version
	Icarus Verilog
$end
$timescale
	1ps
$end
$scope module reg_file_alu_tb $end
$var wire 8 ! cpu_out [7:0] $end
$var wire 1 " Zero $end
$var wire 8 # ALUResult [7:0] $end
$var reg 2 $ ALUControl [1:0] $end
$var reg 1 % ALUSrc $end
$var reg 1 & CLK $end
$var reg 4 ' RA1 [3:0] $end
$var reg 4 ( RA2 [3:0] $end
$var reg 4 ) WA [3:0] $end
$var reg 8 * immediate [7:0] $end
$var reg 1 + write_enable $end
$scope module dut $end
$var wire 2 , ALUControl [1:0] $end
$var wire 1 % ALUSrc $end
$var wire 1 & CLK $end
$var wire 4 - RA1 [3:0] $end
$var wire 4 . RA2 [3:0] $end
$var wire 4 / WA [3:0] $end
$var wire 8 0 cpu_out [7:0] $end
$var wire 8 1 immediate [7:0] $end
$var wire 1 + write_enable $end
$var wire 8 2 SrcB [7:0] $end
$var wire 8 3 RD2 [7:0] $end
$var wire 8 4 RD1 [7:0] $end
$var reg 8 5 ALUResult [7:0] $end
$var reg 1 " Zero $end
$upscope $end
$scope begin $ivl_for_loop0 $end
$var integer 32 6 i [31:0] $end
$upscope $end
$scope begin $ivl_for_loop1 $end
$var integer 32 7 i [31:0] $end
$upscope $end
$upscope $end
$enddefinitions $end
$comment Show the parameter values. $end
$dumpall
$end
#0
$dumpvars
b0 7
b1 6
b1 5
b0 4
bx 3
b1 2
b1 1
bx 0
b1 /
bx .
b0 -
b10 ,
1+
b1 *
b1 )
bx (
b0 '
0&
1%
b10 $
b1 #
0"
bx !
$end
#20000
1&
#40000
b10 #
b10 5
b10 2
b10 *
b10 1
b10 )
b10 /
0&
b10 6
#60000
1&
#80000
b11 #
b11 5
b11 2
b11 *
b11 1
b11 )
b11 /
0&
b11 6
#100000
1&
#120000
b100 #
b100 5
b100 2
b100 *
b100 1
b100 )
b100 /
0&
b100 6
#140000
1&
#160000
b101 #
b101 5
b101 2
b101 *
b101 1
b101 )
b101 /
0&
b101 6
#180000
1&
#200000
b110 #
b110 5
b110 2
b110 *
b110 1
b110 )
b110 /
0&
b110 6
#220000
1&
#240000
b111 #
b111 5
b111 2
b111 *
b111 1
b111 )
b111 /
0&
b111 6
#260000
1&
#280000
b1000 #
b1000 5
b1000 2
b1000 *
b1000 1
b1000 )
b1000 /
0&
b1000 6
#300000
1&
#320000
b1001 #
b1001 5
b1001 2
b1001 *
b1001 1
b1001 )
b1001 /
0&
b1001 6
#340000
1&
#360000
b1010 #
b1010 5
b1010 2
b1010 *
b1010 1
b1010 )
b1010 /
0&
b1010 6
#380000
1&
#400000
b1011 #
b1011 5
b1011 2
b1011 *
b1011 1
b1011 )
b1011 /
0&
b1011 6
#420000
1&
#440000
b1100 #
b1100 5
b1100 2
b1100 *
b1100 1
b1100 )
b1100 /
0&
b1100 6
#460000
1&
#480000
b1101 #
b1101 5
b1101 2
b1101 *
b1101 1
b1101 )
b1101 /
0&
b1101 6
#500000
1&
#520000
b1110 #
b1110 5
b1110 2
b1110 *
b1110 1
b1110 )
b1110 /
0&
b1110 6
#540000
1&
#560000
b1111 #
b1111 5
b1111 2
b1111 *
b1111 1
b1111 )
b1111 /
0&
b1111 6
#580000
b1111 !
b1111 0
1&
#600000
1"
b0 #
b0 5
b0 2
b0 3
b0 *
b0 1
b0 (
b0 .
0+
b10000 6
#620000
0"
b1 #
b1 5
b1 3
b1 4
b1 (
b1 .
b1 '
b1 -
b1 7
#640000
b10 #
b10 5
b10 3
b10 4
b10 (
b10 .
b10 '
b10 -
b10 7
#660000
b11 #
b11 5
b11 3
b11 4
b11 (
b11 .
b11 '
b11 -
b11 7
#680000
b100 #
b100 5
b100 3
b100 4
b100 (
b100 .
b100 '
b100 -
b100 7
#700000
b101 #
b101 5
b101 3
b101 4
b101 (
b101 .
b101 '
b101 -
b101 7
#720000
b110 #
b110 5
b110 3
b110 4
b110 (
b110 .
b110 '
b110 -
b110 7
#740000
b111 #
b111 5
b111 3
b111 4
b111 (
b111 .
b111 '
b111 -
b111 7
#760000
b1000 #
b1000 5
b1000 3
b1000 4
b1000 (
b1000 .
b1000 '
b1000 -
b1000 7
#780000
b1001 #
b1001 5
b1001 3
b1001 4
b1001 (
b1001 .
b1001 '
b1001 -
b1001 7
#800000
b1010 #
b1010 5
b1010 3
b1010 4
b1010 (
b1010 .
b1010 '
b1010 -
b1010 7
#820000
b1011 #
b1011 5
b1011 3
b1011 4
b1011 (
b1011 .
b1011 '
b1011 -
b1011 7
#840000
b1100 #
b1100 5
b1100 3
b1100 4
b1100 (
b1100 .
b1100 '
b1100 -
b1100 7
#860000
b1101 #
b1101 5
b1101 3
b1101 4
b1101 (
b1101 .
b1101 '
b1101 -
b1101 7
#880000
b1110 #
b1110 5
b1110 3
b1110 4
b1110 (
b1110 .
b1110 '
b1110 -
b1110 7
#900000
b1111 #
b1111 5
b1111 3
b1111 4
b1111 (
b1111 .
b1111 '
b1111 -
b1111 7
#920000
b10000 7
