instruction_memory/instruction_memory.sv
module instruction_memory(input logic [7:0] address,
                          output logic [23:0] data_out);

logic [23:0] data_ROM [0:255];
initial
$readmemh("program.txt", data_ROM);
assign data_out = data_ROM[address];
endmodule

instruction_memory/instruction_memory_tb.sv
`timescale 1ns/1ps // Define time units and resolution
`include "instruction_memory.sv" // Include all modules being used in this module

module instruction_memory_tb;
logic [7:0] address;
logic [23:0] data_out;
instruction_memory dut (address,data_out); // Instantiate the module under test. dut (device
// under test) is the name we have chosen

initial begin // Single pass behaviour which starts at time 0 ns
$dumpfile("instruction_memory_tb.vcd"); // Dump variable changes in the vcd file
$dumpvars(0, instruction_memory_tb); // Specifies which variables to dump in the vcd file


for(int i = 0; i<8;i++)
    begin
        address= 8'h00 + i*(8'h01); #20;
    end

end 

initial begin // Single pass behaviour which starts at time 0 ns

$monitor("t = %3d, address = %h, data_out = %h \n", $time, address,data_out);
end // Print variable
// values on screen
endmodule

instruction_memory/instruction_memory_tb.vcd
$date
	Tue Feb 13 17:18:30 2024
$end
$version
	Icarus Verilog
$end
$timescale
	1ps
$end
$scope module instruction_memory_tb $end
$var wire 24 ! data_out [23:0] $end
$var reg 8 " address [7:0] $end
$scope module dut $end
$var wire 8 # address [7:0] $end
$var wire 24 $ data_out [23:0] $end
$upscope $end
$scope begin $ivl_for_loop0 $end
$var integer 32 % i [31:0] $end
$upscope $end
$upscope $end
$enddefinitions $end
$comment Show the parameter values. $end
$dumpall
$end
#0
$dumpvars
b0 %
b11000010000000000000001 $
b0 #
b0 "
b11000010000000000000001 !
$end
#20000
b11000100000000000100000 !
b11000100000000000100000 $
b1 "
b1 #
b1 %
#40000
b11011110000000000000000 !
b11011110000000000000000 $
b10 "
b10 #
b10 %
#60000
b11100000001001000000111 !
b11100000001001000000111 $
b11 "
b11 #
b11 %
#80000
b1000010001000100000000 !
b1000010001000100000000 $
b100 "
b100 #
b100 %
#100000
b11011111111000000000001 !
b11011111111000000000001 $
b101 "
b101 #
b101 %
#120000
b11100000000000000000011 !
b11100000000000000000011 $
b110 "
b110 #
b110 %
#140000
b11100000000000000000111 !
b11100000000000000000111 $
b111 "
b111 #
b111 %
#160000
b1000 %
